kdsl/__init__.py
kdsl/bases.py
kdsl/env.py
kdsl/extra.py
kdsl/py.typed
kdsl/recipe.py
kdsl/utils.py
kdsl/admissionregistration/__init__.py
kdsl/admissionregistration/v1.py
kdsl/apiextensions/__init__.py
kdsl/apiextensions/v1.py
kdsl/apiregistration/__init__.py
kdsl/apiregistration/v1.py
kdsl/apiserverinternal/__init__.py
kdsl/apiserverinternal/v1alpha1.py
kdsl/apps/__init__.py
kdsl/apps/v1.py
kdsl/authentication/__init__.py
kdsl/authentication/v1.py
kdsl/authorization/__init__.py
kdsl/authorization/v1.py
kdsl/autoscaling/__init__.py
kdsl/autoscaling/v1.py
kdsl/autoscaling/v2beta1.py
kdsl/autoscaling/v2beta2.py
kdsl/batch/__init__.py
kdsl/batch/v1.py
kdsl/batch/v1beta1.py
kdsl/certificates/__init__.py
kdsl/certificates/v1.py
kdsl/coordination/__init__.py
kdsl/coordination/v1.py
kdsl/core/__init__.py
kdsl/core/v1.py
kdsl/discovery/__init__.py
kdsl/discovery/v1.py
kdsl/discovery/v1beta1.py
kdsl/events/__init__.py
kdsl/events/v1.py
kdsl/events/v1beta1.py
kdsl/flowcontrol/__init__.py
kdsl/flowcontrol/v1beta1.py
kdsl/networking/__init__.py
kdsl/networking/v1.py
kdsl/node/__init__.py
kdsl/node/v1.py
kdsl/node/v1alpha1.py
kdsl/node/v1beta1.py
kdsl/policy/__init__.py
kdsl/policy/v1.py
kdsl/policy/v1beta1.py
kdsl/rbac/__init__.py
kdsl/rbac/v1.py
kdsl/rbac/v1alpha1.py
kdsl/scheduling/__init__.py
kdsl/scheduling/v1.py
kdsl/scheduling/v1alpha1.py
kdsl/storage/__init__.py
kdsl/storage/v1.py
kdsl/storage/v1alpha1.py
kdsl/storage/v1beta1.py
kdsl-1.22.4.dist-info/METADATA
kdsl-1.22.4.dist-info/WHEEL
kdsl-1.22.4.dist-info/top_level.txt
kdsl-1.22.4.dist-info/RECORD
