Metadata-Version: 2.1
Name: kdsl
Version: 1.22.4
Summary: Kubernetes DSL
Home-page: https://gitlab.com/qwolphin/kdsl
Author: Wolphin
Author-email: q@wolph.in
License: UNKNOWN
Platform: UNKNOWN
Classifier: Typing :: Typed
Classifier: Development Status :: 2 - Pre-Alpha
Classifier: Intended Audience :: Developers
Classifier: Natural Language :: English
Classifier: License :: OSI Approved :: MIT License
Classifier: Programming Language :: Python
Classifier: Programming Language :: Python :: 3
Requires-Dist: attrs
Requires-Dist: pyyaml
Requires-Dist: envparse
Requires-Dist: python-dotenv
